zlest1/__init__.py
zlest1/bidding_sinopec_com.py
zlest1/cgw_xjbt_gov_cn.py
zlest1/eps_shmetro_com.py
zlest1/mall_cdtbuy_cn.py
zlest1/qg_ggzy.py
zlest1/qg_zfcg.py
zlest1/scs_inspur_com.py
zlest1/sdhsg_com.py
zlest1/task.py
zlest1/www_bidding_citic.py
zlest1/www_ceiea_com.py
zlest1/www_cfcpn_com.py
zlest1/www_cntec_com_cn.py
zlest1/www_gcbidding_com.py
zlest1/www_guangxibid_com_cn.py
zlest1/www_gztpc_com.py
zlest1/www_haierbid_com.py
zlest1/www_hnbidding_com.py
zlest1/www_hnsl_gov_cn.py
zlest1/www_hnzbcg_com_cn.py
zlest1/www_jxtb_org_cn.py
zlest1/www_sntba_com.py
zlest1/www_soeasyjc_com.py
zlest1/www_sxzzgs_com.py
zlest1/www_tsjj_com_cn.py
zlest1/www_ztgh_com_cn.py
zlest1/www_zybtp_com.py
zlest1/zbb_nankai_edu_cn.py
zlest1/zbcg_nenu_edu_cn.py
zlest1/zc_gtcloud_cn.py
zlest1/util/__init__.py
zlest1/util/cfg_db
zlest1/util/conf.py
zlest1/util/etl.py
zlest1/util/fake_useragent.py
zlest1/util/test.py
zlest1-1.0.8.dist-info/METADATA
zlest1-1.0.8.dist-info/WHEEL
zlest1-1.0.8.dist-info/top_level.txt
zlest1-1.0.8.dist-info/RECORD
